elasticbud/__init__.py
elasticbud/asyncelasticsearch.py
elasticbud/client.py
elasticbud/elasticsearch.py
elasticbud/errors.py
elasticbud/logger.py
elasticbud/utils.py
elasticbud-1.3.0.dist-info/WHEEL
elasticbud-1.3.0.dist-info/METADATA
elasticbud-1.3.0.dist-info/RECORD
